itwalker/__init__.py
itwalker/common.py
itwalker/db_helper.py
itwalker/http_helper.py
itwalker/log_helper.py
itwalker/param_handle.py
itwalker/rsa_helper.py
itwalker-2.5.2.dist-info/METADATA
itwalker-2.5.2.dist-info/WHEEL
itwalker-2.5.2.dist-info/top_level.txt
itwalker-2.5.2.dist-info/RECORD
